config.py
main.py
allensrj_cdisc_library_mcp-0.1.1.dist-info/licenses/LICENSE
tools/__init__.py
tools/adam.py
tools/general.py
tools/sdtm.py
tools/terminology.py
utils/__init__.py
utils/formatters.py
utils/http_client.py
allensrj_cdisc_library_mcp-0.1.1.dist-info/METADATA
allensrj_cdisc_library_mcp-0.1.1.dist-info/WHEEL
allensrj_cdisc_library_mcp-0.1.1.dist-info/entry_points.txt
allensrj_cdisc_library_mcp-0.1.1.dist-info/top_level.txt
allensrj_cdisc_library_mcp-0.1.1.dist-info/RECORD
