Metadata-Version: 2.4
Name: allensrj-cdisc-library-mcp
Version: 0.1.1
Summary: CDISC Library MCP server: SDTM, ADaM, CDASH, Controlled Terminology tools for AI assistants
License: MIT
Requires-Python: >=3.10
License-File: LICENSE
Requires-Dist: mcp[cli]>=1.26.0
Requires-Dist: httpx>=0.27.0
Requires-Dist: python-dotenv>=1.0.0
Provides-Extra: dev
Requires-Dist: build>=1.0.0; extra == "dev"
Requires-Dist: twine>=5.0.0; extra == "dev"
Dynamic: license-file
